caen_libs/__init__.py
caen_libs/_cache.py
caen_libs/_caencommtypes.py
caen_libs/_caendigitizertypes.py
caen_libs/_caendpplibtypes.py
caen_libs/_caenhvwrappertypes.py
caen_libs/_caenplutypes.py
caen_libs/_caenvmetypes.py
caen_libs/_string.py
caen_libs/_utils.py
caen_libs/caencomm.py
caen_libs/caendigitizer.py
caen_libs/caendpplib.py
caen_libs/caenhvwrapper.py
caen_libs/caenhvwrapperflags.py
caen_libs/caenplu.py
caen_libs/caenvme.py
caen_libs/error.py
caen_libs/py.typed
caen_libs-3.2.0.dist-info/licenses/COPYING
caen_libs-3.2.0.dist-info/licenses/COPYING.LESSER
caen_libs-3.2.0.dist-info/METADATA
caen_libs-3.2.0.dist-info/WHEEL
caen_libs-3.2.0.dist-info/top_level.txt
caen_libs-3.2.0.dist-info/RECORD
