Metadata-Version: 2.4
Name: caen_libs
Version: 3.2.0
Summary: Official Python binding for CAEN VMELib, CAEN Comm, CAEN Digitizer, CAEN PLU, CAEN HV Wrapper and CAEN DPP Library.
Author: Giovanni Cerretani
Project-URL: Homepage, https://www.caen.it
Project-URL: Support, https://www.caen.it/mycaen/support/
Project-URL: Source, https://github.com/caenspa/py-caen-libs
Project-URL: Changelog, https://github.com/caenspa/py-caen-libs/blob/main/PYCHANGELOG
Classifier: Development Status :: 5 - Production/Stable
Classifier: Intended Audience :: Science/Research
Classifier: License :: OSI Approved :: GNU Lesser General Public License v3 or later (LGPLv3+)
Classifier: Natural Language :: English
Classifier: Operating System :: Microsoft :: Windows
Classifier: Operating System :: POSIX :: Linux
Classifier: Programming Language :: Python :: 3
Classifier: Programming Language :: Python :: 3.10
Classifier: Programming Language :: Python :: 3.11
Classifier: Programming Language :: Python :: 3.12
Classifier: Programming Language :: Python :: 3.13
Classifier: Programming Language :: Python :: 3.14
Classifier: Topic :: Scientific/Engineering :: Physics
Classifier: Typing :: Typed
Requires-Python: >=3.10
License-File: COPYING
License-File: COPYING.LESSER
Requires-Dist: numpy>=2.0
Dynamic: license-file
